{
  "taskDefinition": {
    "family": "reports-django-docker-aws",
    "containerDefinitions": [
      {
        "name": "reports-django-docker-aws",
        "image": "383820954082.dkr.ecr.eu-central-1.amazonaws.com/reports-django-docker-aws:6a57b99",
        "cpu": 100,
        "portMappings": [
          {
            "protocol": "tcp",
            "containerPort": 8000,
            "hostPort": 8000
          }
        ],
        "memory": 128,
        "essential": true
      }
    ],
    "volumes": [],
    "networkMode": "awsvpc",
    "memory": "512",
    "cpu": "256",
    "executionRoleArn": "<create_new>",
    "family": "reports-django-docker-aws",
    "tags": [],
    "requiresCompatibilities": [
        "FARGATE"
    ]
  }
}
